sked/__init__.py
sked/__main__.py
sked/cli.py
sked/commands/__init__.py
sked/commands/basecommand.py
sked/commands/create.py
sked/commands/delete.py
sked/common/__init__.py
sked/common/aws_client.py
sked/common/aws_helper.py
sked/common/config_parser.py
sked/common/yaml_parser.py
sked-1.0.0.dist-info/METADATA
sked-1.0.0.dist-info/RECORD
sked-1.0.0.dist-info/WHEEL
sked-1.0.0.dist-info/entry_points.txt
sked-1.0.0.dist-info/top_level.txt
