Metadata-Version: 2.1
Name: sked
Version: 1.0.0
Summary: CLI utility to create AWS Scheduled Actions using instance tags or autoscaling id via a config file
Home-page: https://github.com/niklongstone/sked
Author: Nicola Pietroluongo
Author-email: nik.longstone@gmail.com
License: MIT
Keywords: cli,aws,scaling,auto scaling group,scheduled actions
Platform: UNKNOWN
Classifier: Intended Audience :: Developers
Classifier: Topic :: Internet
Classifier: License :: OSI Approved :: MIT License
Classifier: Natural Language :: English
Classifier: Operating System :: OS Independent
Classifier: Programming Language :: Python :: 2
Classifier: Programming Language :: Python :: 2.6
Classifier: Programming Language :: Python :: 2.7
Classifier: Programming Language :: Python :: 3
Classifier: Programming Language :: Python :: 3.3
Classifier: Programming Language :: Python :: 3.4
Classifier: Programming Language :: Python :: 3.5
Classifier: Programming Language :: Python :: 3.6
Provides-Extra: test
Requires-Dist: docopt
Requires-Dist: boto3
Requires-Dist: PyYAML
Requires-Dist: mock; python_version in "2.6, 2.7"
Provides-Extra: test
Requires-Dist: coverage; extra == 'test'
Requires-Dist: pytest; extra == 'test'
Requires-Dist: pytest-cov; extra == 'test'
Requires-Dist: tox; extra == 'test'
